{
  "api": "2",
  "auth": "cpan:MARTIMM",
  "author": "Marcel Timmerman",
  "authors": [
  ],
  "depends": [
    "Gnome::N:api<2>"
  ],
  "description": "Modules for package Gnome::Glib:api<2>. The language binding to GNOME's lowest level library",
  "license": "Artistic-2.0",
  "meta-version": "2",
  "name": "Gnome::Glib",
  "provides": {
    "Gnome::Glib::Error": "lib/Gnome/Glib/Error.rakumod",
    "Gnome::Glib::List": "lib/Gnome/Glib/List.rakumod",
    "Gnome::Glib::MainContext": "lib/Gnome/Glib/MainContext.rakumod",
    "Gnome::Glib::MainLoop": "lib/Gnome/Glib/MainLoop.rakumod",
    "Gnome::Glib::N-Error": "lib/Gnome/Glib/N-Error.rakumod",
    "Gnome::Glib::N-List": "lib/Gnome/Glib/N-List.rakumod",
    "Gnome::Glib::N-MainContext": "lib/Gnome/Glib/N-MainContext.rakumod",
    "Gnome::Glib::N-MainLoop": "lib/Gnome/Glib/N-MainLoop.rakumod",
    "Gnome::Glib::N-SList": "lib/Gnome/Glib/N-SList.rakumod",
    "Gnome::Glib::N-Variant": "lib/Gnome/Glib/N-Variant.rakumod",
    "Gnome::Glib::N-VariantDict": "lib/Gnome/Glib/N-VariantDict.rakumod",
    "Gnome::Glib::N-VariantType": "lib/Gnome/Glib/N-VariantType.rakumod",
    "Gnome::Glib::SList": "lib/Gnome/Glib/SList.rakumod",
    "Gnome::Glib::T-Error": "lib/Gnome/Glib/T-Error.rakumod",
    "Gnome::Glib::T-List": "lib/Gnome/Glib/T-List.rakumod",
    "Gnome::Glib::T-MainContext": "lib/Gnome/Glib/T-MainContext.rakumod",
    "Gnome::Glib::T-Quark": "lib/Gnome/Glib/T-Quark.rakumod",
    "Gnome::Glib::T-SList": "lib/Gnome/Glib/T-SList.rakumod",
    "Gnome::Glib::T-Variant": "lib/Gnome/Glib/T-Variant.rakumod",
    "Gnome::Glib::Variant": "lib/Gnome/Glib/Variant.rakumod",
    "Gnome::Glib::VariantDict": "lib/Gnome/Glib/VariantDict.rakumod",
    "Gnome::Glib::VariantType": "lib/Gnome/Glib/VariantType.rakumod"
  },
  "raku": null,
  "resources": [
  ],
  "source-url": "git://github.com/MARTIMM/gnome-glib-api2.git",
  "support": {
    "source": null
  },
  "tags": [
    "Gnome",
    "Glib"
  ],
  "version": "0.1.3"
}